[
    {
        "Nodo0": {
            "FPGA": [
                [
                    {
                        "Modelo": "G",
                        "Part0": {
                            "BRAM": 192,
                            "CLB": 6960,
                            "DSP": 96,
                            "IO": 0
                        },
                        "Part1": {
                            "BRAM": 576,
                            "CLB": 17280,
                            "DSP": 192,
                            "IO": 0
                        },
                        "Part2": {
                            "BRAM": 216,
                            "CLB": 9180,
                            "DSP": 144,
                            "IO": 0
                        },
                        "Part3": {
                            "BRAM": 216,
                            "CLB": 9180,
                            "DSP": 144,
                            "IO": 0
                        },
                        "Part4": {
                            "BRAM": 384,
                            "CLB": 13920,
                            "DSP": 192,
                            "IO": 8
                        },
                        "Part5": {
                            "BRAM": 192,
                            "CLB": 7200,
                            "DSP": 192,
                            "IO": 0
                        },
                        "Part6": {
                            "BRAM": 216,
                            "CLB": 9180,
                            "DSP": 144,
                            "IO": 0
                        },
                        "Part7": {
                            "BRAM": 216,
                            "CLB": 9180,
                            "DSP": 144,
                            "IO": 0
                        }
                    }
                ],
                [
                    {
                        "Modelo": "G",
                        "Part0": {
                            "BRAM": 900,
                            "CLB": 28800,
                            "DSP": 360,
                            "IO": 0
                        },
                        "Part1": {
                            "BRAM": 360,
                            "CLB": 15300,
                            "DSP": 240,
                            "IO": 0
                        },
                        "Part2": {
                            "BRAM": 600,
                            "CLB": 23400,
                            "DSP": 480,
                            "IO": 0
                        },
                        "Part3": {
                            "BRAM": 192,
                            "CLB": 7200,
                            "DSP": 192,
                            "IO": 0
                        }
                    }
                ],
                [
                    {
                        "Modelo": "G",
                        "Part0": {
                            "BRAM": 336,
                            "CLB": 10080,
                            "DSP": 96,
                            "IO": 0
                        },
                        "Part1": {
                            "BRAM": 792,
                            "CLB": 33660,
                            "DSP": 528,
                            "IO": 0
                        },
                        "Part2": {
                            "BRAM": 384,
                            "CLB": 13920,
                            "DSP": 192,
                            "IO": 8
                        },
                        "Part3": {
                            "BRAM": 216,
                            "CLB": 6960,
                            "DSP": 96,
                            "IO": 8
                        },
                        "Part4": {
                            "BRAM": 192,
                            "CLB": 7200,
                            "DSP": 192,
                            "IO": 0
                        },
                        "Part5": {
                            "BRAM": 288,
                            "CLB": 9360,
                            "DSP": 96,
                            "IO": 0
                        }
                    }
                ]
            ],
            "Links": [
                {
                    "2": {
                        "Lat": 140,
                        "Throughput": 200
                    }
                },
                {
                    "4": {
                        "Lat": 188,
                        "Throughput": 100
                    }
                },
                {
                    "5": {
                        "Lat": 55,
                        "Throughput": 200
                    }
                }
            ]
        },
        "Nodo1": {
            "FPGA": [
                [
                    {
                        "Modelo": "G",
                        "Part0": {
                            "BRAM": 216,
                            "CLB": 9180,
                            "DSP": 144,
                            "IO": 0
                        },
                        "Part1": {
                            "BRAM": 384,
                            "CLB": 13920,
                            "DSP": 192,
                            "IO": 0
                        },
                        "Part2": {
                            "BRAM": 384,
                            "CLB": 13920,
                            "DSP": 192,
                            "IO": 8
                        },
                        "Part3": {
                            "BRAM": 360,
                            "CLB": 15300,
                            "DSP": 240,
                            "IO": 0
                        },
                        "Part4": {
                            "BRAM": 192,
                            "CLB": 6960,
                            "DSP": 96,
                            "IO": 0
                        },
                        "Part5": {
                            "BRAM": 192,
                            "CLB": 7200,
                            "DSP": 192,
                            "IO": 0
                        },
                        "Part6": {
                            "BRAM": 192,
                            "CLB": 7320,
                            "DSP": 96,
                            "IO": 4
                        }
                    }
                ]
            ],
            "Links": [
                {
                    "7": {
                        "Lat": 107,
                        "Throughput": 200
                    }
                },
                {
                    "4": {
                        "Lat": 153,
                        "Throughput": 200
                    }
                },
                {
                    "2": {
                        "Lat": 142,
                        "Throughput": 40
                    }
                }
            ]
        },
        "Nodo2": {
            "FPGA": [
                [
                    {
                        "Modelo": "G",
                        "Part0": {
                            "BRAM": 672,
                            "CLB": 22560,
                            "DSP": 192,
                            "IO": 0
                        },
                        "Part1": {
                            "BRAM": 792,
                            "CLB": 33660,
                            "DSP": 528,
                            "IO": 0
                        },
                        "Part2": {
                            "BRAM": 192,
                            "CLB": 6960,
                            "DSP": 96,
                            "IO": 0
                        },
                        "Part3": {
                            "BRAM": 216,
                            "CLB": 6960,
                            "DSP": 96,
                            "IO": 4
                        },
                        "Part4": {
                            "BRAM": 192,
                            "CLB": 6960,
                            "DSP": 96,
                            "IO": 4
                        },
                        "Part5": {
                            "BRAM": 192,
                            "CLB": 7200,
                            "DSP": 192,
                            "IO": 0
                        }
                    }
                ]
            ],
            "Links": [
                {
                    "0": {
                        "Lat": 111,
                        "Throughput": 400
                    }
                },
                {
                    "1": {
                        "Lat": 51,
                        "Throughput": 100
                    }
                },
                {
                    "5": {
                        "Lat": 157,
                        "Throughput": 200
                    }
                }
            ]
        },
        "Nodo3": {
            "FPGA": [
                [
                    {
                        "Modelo": "G",
                        "Part0": {
                            "BRAM": 240,
                            "CLB": 7800,
                            "DSP": 120,
                            "IO": 0
                        },
                        "Part1": {
                            "BRAM": 792,
                            "CLB": 33000,
                            "DSP": 528,
                            "IO": 0
                        },
                        "Part2": {
                            "BRAM": 480,
                            "CLB": 15600,
                            "DSP": 240,
                            "IO": 0
                        },
                        "Part3": {
                            "BRAM": 216,
                            "CLB": 6960,
                            "DSP": 96,
                            "IO": 4
                        },
                        "Part4": {
                            "BRAM": 192,
                            "CLB": 7200,
                            "DSP": 192,
                            "IO": 0
                        }
                    }
                ],
                [
                    {
                        "Modelo": "G",
                        "Part0": {
                            "BRAM": 216,
                            "CLB": 9180,
                            "DSP": 144,
                            "IO": 0
                        },
                        "Part1": {
                            "BRAM": 384,
                            "CLB": 13920,
                            "DSP": 192,
                            "IO": 8
                        },
                        "Part2": {
                            "BRAM": 384,
                            "CLB": 13920,
                            "DSP": 192,
                            "IO": 0
                        },
                        "Part3": {
                            "BRAM": 408,
                            "CLB": 13920,
                            "DSP": 192,
                            "IO": 8
                        },
                        "Part4": {
                            "BRAM": 240,
                            "CLB": 8640,
                            "DSP": 192,
                            "IO": 0
                        },
                        "Part5": {
                            "BRAM": 216,
                            "CLB": 9180,
                            "DSP": 144,
                            "IO": 0
                        },
                        "Part6": {
                            "BRAM": 192,
                            "CLB": 7200,
                            "DSP": 192,
                            "IO": 0
                        }
                    }
                ],
                [
                    {
                        "Modelo": "G",
                        "Part0": {
                            "BRAM": 672,
                            "CLB": 20160,
                            "DSP": 192,
                            "IO": 0
                        },
                        "Part1": {
                            "BRAM": 384,
                            "CLB": 13920,
                            "DSP": 192,
                            "IO": 8
                        },
                        "Part2": {
                            "BRAM": 360,
                            "CLB": 15300,
                            "DSP": 240,
                            "IO": 0
                        },
                        "Part3": {
                            "BRAM": 360,
                            "CLB": 15300,
                            "DSP": 240,
                            "IO": 0
                        },
                        "Part4": {
                            "BRAM": 192,
                            "CLB": 7200,
                            "DSP": 192,
                            "IO": 0
                        },
                        "Part5": {
                            "BRAM": 216,
                            "CLB": 6960,
                            "DSP": 96,
                            "IO": 4
                        }
                    }
                ]
            ],
            "Links": [
                {
                    "5": {
                        "Lat": 169,
                        "Throughput": 400
                    }
                },
                {
                    "6": {
                        "Lat": 115,
                        "Throughput": 40
                    }
                }
            ]
        },
        "Nodo4": {
            "FPGA": [],
            "Links": [
                {
                    "0": {
                        "Lat": 44,
                        "Throughput": 400
                    }
                },
                {
                    "1": {
                        "Lat": 133,
                        "Throughput": 100
                    }
                }
            ]
        },
        "Nodo5": {
            "FPGA": [
                [
                    {
                        "Modelo": "G",
                        "Part0": {
                            "BRAM": 936,
                            "CLB": 39780,
                            "DSP": 624,
                            "IO": 0
                        },
                        "Part1": {
                            "BRAM": 288,
                            "CLB": 11040,
                            "DSP": 144,
                            "IO": 4
                        },
                        "Part2": {
                            "BRAM": 192,
                            "CLB": 6960,
                            "DSP": 96,
                            "IO": 4
                        },
                        "Part3": {
                            "BRAM": 192,
                            "CLB": 6960,
                            "DSP": 96,
                            "IO": 0
                        },
                        "Part4": {
                            "BRAM": 192,
                            "CLB": 6960,
                            "DSP": 96,
                            "IO": 0
                        },
                        "Part5": {
                            "BRAM": 192,
                            "CLB": 7200,
                            "DSP": 192,
                            "IO": 0
                        },
                        "Part6": {
                            "BRAM": 216,
                            "CLB": 6960,
                            "DSP": 96,
                            "IO": 4
                        }
                    }
                ]
            ],
            "Links": [
                {
                    "0": {
                        "Lat": 73,
                        "Throughput": 100
                    }
                },
                {
                    "2": {
                        "Lat": 170,
                        "Throughput": 200
                    }
                },
                {
                    "3": {
                        "Lat": 141,
                        "Throughput": 40
                    }
                }
            ]
        },
        "Nodo6": {
            "FPGA": [],
            "Links": [
                {
                    "3": {
                        "Lat": 77,
                        "Throughput": 100
                    }
                },
                {
                    "7": {
                        "Lat": 56,
                        "Throughput": 200
                    }
                }
            ]
        },
        "Nodo7": {
            "FPGA": [
                [
                    {
                        "Modelo": "G",
                        "Part0": {
                            "BRAM": 192,
                            "CLB": 6960,
                            "DSP": 96,
                            "IO": 0
                        },
                        "Part1": {
                            "BRAM": 192,
                            "CLB": 9600,
                            "DSP": 192,
                            "IO": 0
                        },
                        "Part2": {
                            "BRAM": 792,
                            "CLB": 33660,
                            "DSP": 528,
                            "IO": 0
                        },
                        "Part3": {
                            "BRAM": 240,
                            "CLB": 8160,
                            "DSP": 96,
                            "IO": 0
                        },
                        "Part4": {
                            "BRAM": 192,
                            "CLB": 6960,
                            "DSP": 96,
                            "IO": 4
                        },
                        "Part5": {
                            "BRAM": 192,
                            "CLB": 6960,
                            "DSP": 96,
                            "IO": 0
                        },
                        "Part6": {
                            "BRAM": 336,
                            "CLB": 10800,
                            "DSP": 144,
                            "IO": 8
                        }
                    }
                ],
                [
                    {
                        "Modelo": "G",
                        "Part0": {
                            "BRAM": 432,
                            "CLB": 14040,
                            "DSP": 216,
                            "IO": 0
                        },
                        "Part1": {
                            "BRAM": 792,
                            "CLB": 33660,
                            "DSP": 528,
                            "IO": 0
                        },
                        "Part2": {
                            "BRAM": 432,
                            "CLB": 15840,
                            "DSP": 240,
                            "IO": 8
                        },
                        "Part3": {
                            "BRAM": 192,
                            "CLB": 9120,
                            "DSP": 192,
                            "IO": 0
                        },
                        "Part4": {
                            "BRAM": 216,
                            "CLB": 6960,
                            "DSP": 96,
                            "IO": 8
                        }
                    }
                ],
                [
                    {
                        "Modelo": "G",
                        "Part0": {
                            "BRAM": 624,
                            "CLB": 20280,
                            "DSP": 312,
                            "IO": 0
                        },
                        "Part1": {
                            "BRAM": 360,
                            "CLB": 15300,
                            "DSP": 240,
                            "IO": 0
                        },
                        "Part2": {
                            "BRAM": 360,
                            "CLB": 15300,
                            "DSP": 240,
                            "IO": 0
                        },
                        "Part3": {
                            "BRAM": 192,
                            "CLB": 7200,
                            "DSP": 192,
                            "IO": 0
                        },
                        "Part4": {
                            "BRAM": 216,
                            "CLB": 6960,
                            "DSP": 96,
                            "IO": 8
                        },
                        "Part5": {
                            "BRAM": 360,
                            "CLB": 15300,
                            "DSP": 240,
                            "IO": 0
                        }
                    }
                ]
            ],
            "Links": [
                {
                    "1": {
                        "Lat": 109,
                        "Throughput": 100
                    }
                },
                {
                    "6": {
                        "Lat": 22,
                        "Throughput": 100
                    }
                }
            ]
        }
    }
]